LICENSE
README.md
setup.py
otssql/__init__.py
otssql/connection.py
otssql/cursor.py
otssql/exceptions.py
otssql/metasequoia_enhance.py
otssql/times.py
otssql.egg-info/PKG-INFO
otssql.egg-info/SOURCES.txt
otssql.egg-info/dependency_links.txt
otssql.egg-info/requires.txt
otssql.egg-info/top_level.txt
otssql/constants/__init__.py
otssql/constants/field_type.py
otssql/convert/__init__.py
otssql/convert/aggregation_function.py
otssql/convert/limit_clause.py
otssql/convert/order_by_clause.py
otssql/convert/table_name.py
otssql/convert/update_set_clause.py
otssql/convert/where_clause.py
otssql/sdk_api/__init__.py
otssql/sdk_api/do_delete.py
otssql/sdk_api/do_query.py
otssql/sdk_api/do_update.py
otssql/sdk_api/get_index_field_set.py
otssql/strategy/__init__.py
otssql/strategy/choose_tablestore_index.py
otssql/strategy/detect_type.py
otssql/strategy/execute_delete.py
otssql/strategy/execute_select_aggregation.py
otssql/strategy/execute_select_group_by.py
otssql/strategy/execute_select_normal.py
otssql/strategy/execute_update.py