Metadata-Version: 2.1
Name: otssql
Version: 0.1.0
Summary: 阿里云 tablestore 的 Python Database API 2.0 连接器（支持 SDK SQL 查询中不支持的 UPDATE 和 DELETE 语句）
Home-page: https://github.com/ChangxingJiang/otssql
Author: changxing
Author-email: 1278729001@qq.com
License: MIT License
Platform: all
Classifier: Intended Audience :: Developers
Classifier: Operating System :: OS Independent
Classifier: Natural Language :: Chinese (Simplified)
Classifier: Programming Language :: Python
Classifier: Programming Language :: Python :: 3.10
Classifier: Programming Language :: Python :: 3.11
Classifier: Programming Language :: Python :: 3.12
Classifier: Topic :: Software Development :: Libraries
License-File: LICENSE
Requires-Dist: metasequoia-sql
Requires-Dist: tablestore
